{
  "students": [
    {
      "avatar_url": "https://images.unsplash.com/photo-1502767882403-636aee14f873?ixlib=rb-1.2.1&ixid=eyJhcHBfaWQiOjEyMDd9&auto=format&fit=crop&w=334&q=80",
      "name": "Maria Silva",
      "email": "maria@site.com",
      "birth": 641692800000,
      "grade": "3",
      "hours": "4",
      "id": "1"
    }
  ],
  "teachers": [
    {
      "id": 1,
      "name": "Joao",
      "avatar_url": "https://images.unsplash.com/photo-1473492201326-7c01dd2e596b?ixlib=rb-1.2.1&ixid=eyJhcHBfaWQiOjEyMDd9&auto=format&fit=crop&w=751&q=80",
      "birth": 263692800000,
      "created_at": 1593970144883,
      "degree": "master",
      "classType": "D",
      "services": "Literatura, Português"
    }
  ]
}